ringer_business/__init__.py
ringer_business/api_client.py
ringer_business/api_response.py
ringer_business/configuration.py
ringer_business/exceptions.py
ringer_business/py.typed
ringer_business/rest.py
ringer_business/api/__init__.py
ringer_business/api/accounts_api.py
ringer_business/api/addresses_api.py
ringer_business/api/authentication_api.py
ringer_business/api/call_records_api.py
ringer_business/api/confirmation_api.py
ringer_business/api/country_codes_api.py
ringer_business/api/credit_cards_api.py
ringer_business/api/items_api.py
ringer_business/api/packages_api.py
ringer_business/api/password_management_api.py
ringer_business/api/payments_api.py
ringer_business/api/phone_number_search_api.py
ringer_business/api/plans_api.py
ringer_business/api/sign_up_api.py
ringer_business/api/site_features_call_blocking_api.py
ringer_business/api/site_features_conference_rooms_api.py
ringer_business/api/site_features_devices_api.py
ringer_business/api/site_features_e911_api.py
ringer_business/api/site_features_extensions_api.py
ringer_business/api/site_features_fax_machines_api.py
ringer_business/api/site_features_forwards_api.py
ringer_business/api/site_features_locations_api.py
ringer_business/api/site_features_menus_api.py
ringer_business/api/site_features_phone_numbers_api.py
ringer_business/api/site_features_ring_groups_api.py
ringer_business/api/site_features_schedules_api.py
ringer_business/api/site_features_seats_api.py
ringer_business/api/site_features_sip_trunks_api.py
ringer_business/api/site_features_voicemail_boxes_api.py
ringer_business/api/sites_api.py
ringer_business/api/statements_api.py
ringer_business/api/templates_api.py
ringer_business/api/thin_clients_api.py
ringer_business/api/timezones_api.py
ringer_business/api/users_api.py
ringer_business/models/__init__.py
ringer_business/models/account_response.py
ringer_business/models/account_update_request.py
ringer_business/models/address_core.py
ringer_business/models/address_registered.py
ringer_ivy-1.0.6.dist-info/METADATA
ringer_ivy-1.0.6.dist-info/WHEEL
ringer_ivy-1.0.6.dist-info/top_level.txt
ringer_ivy-1.0.6.dist-info/RECORD
