Metadata-Version: 2.1
Name: ringer-ivy
Version: 1.0.6
Summary: Ringer Business API
Home-page: 
Author: Ringer API Support
Author-email: support@ringer.tel
License: MIT License
Keywords: OpenAPI,OpenAPI-Generator,Ringer Business API
Requires-Dist: urllib3<3.0.0,>=2.1.0
Requires-Dist: python-dateutil>=2.8.2
Requires-Dist: pydantic>=2
Requires-Dist: typing-extensions>=4.7.1
